pyodds/__init__.py
pyodds/algo/__init__.py
pyodds/algo/algorithm_utils.py
pyodds/algo/autoencoder.py
pyodds/algo/base.py
pyodds/algo/cblof.py
pyodds/algo/dagmm.py
pyodds/algo/hbos.py
pyodds/algo/iforest.py
pyodds/algo/knn.py
pyodds/algo/lof.py
pyodds/algo/lstmad.py
pyodds/algo/lstmencdec.py
pyodds/algo/luminolFunc.py
pyodds/algo/ocsvm.py
pyodds/algo/pca.py
pyodds/algo/robustcovariance.py
pyodds/algo/sod.py
pyodds/algo/staticautoencoder.py
pyodds/utils/__init__.py
pyodds/utils/importAlgorithm.py
pyodds/utils/plotUtils.py
pyodds/utils/utilities.py
pyodds-1.0.0rc1.dist-info/LICENSE
pyodds-1.0.0rc1.dist-info/METADATA
pyodds-1.0.0rc1.dist-info/WHEEL
pyodds-1.0.0rc1.dist-info/top_level.txt
pyodds-1.0.0rc1.dist-info/RECORD
