Metadata-Version: 2.1
Name: pyodds
Version: 1.0.0rc1
Summary: An end-to-end anomaly detection system
Home-page: https://github.com/datamllab/PyODDS
Author: Data Analytics at Texas A&M (DATA) Lab, Yuening Li
Author-email: yuehningli@gmail.com
License: UNKNOWN
Platform: UNKNOWN
Requires-Python: >=3.5
Requires-Dist: pandas (>=0.24.0)
Requires-Dist: tensorflow (==2.0.0b1)
Requires-Dist: numpy (>=1.16.4)
Requires-Dist: seaborn (>=0.9.0)
Requires-Dist: torch (>=1.1.0)
Requires-Dist: luminol (==0.4)
Requires-Dist: tqdm (>=4.35.0)
Requires-Dist: matplotlib (>=3.0.0)
Requires-Dist: scikit-learn (>=0.21.3)
